ConfigParserList/__init__.py
ConfigParserList/configparserlist.py
configparser_list-1.0.0.dist-info/LICENSE
configparser_list-1.0.0.dist-info/METADATA
configparser_list-1.0.0.dist-info/WHEEL
configparser_list-1.0.0.dist-info/top_level.txt
configparser_list-1.0.0.dist-info/RECORD
