Metadata-Version: 2.1
Name: configparser-list
Version: 1.0.0
Summary: Extends ConfigParser to support lists
Author-email: Ahmad Alobaid <aalobaid@fi.upm.es>
License: Apache License
Project-URL: Homepage, https://github.com/ahmad88me/configparser-list
Keywords: configparser,config,parser,configparser-list,configparserlist
Classifier: Programming Language :: Python
Classifier: Programming Language :: Python :: 3
Classifier: License :: OSI Approved :: Apache Software License
Requires-Python: >=3.0
License-File: LICENSE
Requires-Dist: tomli ; python_version > "3.0"
Provides-Extra: dev
Requires-Dist: codecov ; extra == 'dev'
Requires-Dist: twine ; extra == 'dev'
